django_state_machines/__init__.py
django_state_machines/data_classes.py
django_state_machines/decorators.py
django_state_machines/exceptions.py
django_state_machines/fields.py
django_state_machines/helpers.py
django_state_machines/logic.py
django_state_machines/state_map.py
django_state_machines-0.1.2.dist-info/DESCRIPTION.rst
django_state_machines-0.1.2.dist-info/METADATA
django_state_machines-0.1.2.dist-info/RECORD
django_state_machines-0.1.2.dist-info/WHEEL
django_state_machines-0.1.2.dist-info/metadata.json
django_state_machines-0.1.2.dist-info/top_level.txt
